ataqc/__init__.py
ataqc/ataqc
ataqc/integrative.py
ataqc/peaks.py
ataqc/qc.py
ataqc/reads.py
ataqc/viz.py
ataqc-0.2.data/scripts/ataqc
ataqc-0.2.dist-info/DESCRIPTION.rst
ataqc-0.2.dist-info/METADATA
ataqc-0.2.dist-info/RECORD
ataqc-0.2.dist-info/WHEEL
ataqc-0.2.dist-info/metadata.json
ataqc-0.2.dist-info/top_level.txt
