Metadata-Version: 2.0
Name: ataqc
Version: 0.2
Summary: ATAqC - quality control for ATAC-seq
Home-page: https://github.com/kundajelab/ataqc
Author: Chuan-Sheng Foo, Daniel Kim
Author-email: csfoo@cs.stanford.edu
License: BSD-3
Keywords: ATAC-seq bioinformatics QC genomics
Platform: UNKNOWN
Classifier: Development Status :: 3 - Alpha
Classifier: Intended Audience :: Science/Research
Classifier: Intended Audience :: Developers
Classifier: Topic :: Scientific/Engineering
Classifier: License :: OSI Approved :: BSD License
Classifier: Programming Language :: Python :: 2.7
Classifier: Operating System :: POSIX :: Linux
Requires-Dist: jinja2
Requires-Dist: matplotlib (>=1.5.1)
Requires-Dist: metaseq (==0.5.6)
Requires-Dist: numpy (>=1.10.2)
Requires-Dist: pandas
Requires-Dist: pybedtools (>=0.6.9)
Requires-Dist: pysam (>=0.8.2.1)
Requires-Dist: scipy
